simple_pyyuque.py
simple_pyyuque-0.1.3.dist-info/LICENSE
simple_pyyuque-0.1.3.dist-info/METADATA
simple_pyyuque-0.1.3.dist-info/WHEEL
simple_pyyuque-0.1.3.dist-info/top_level.txt
simple_pyyuque-0.1.3.dist-info/RECORD
