Metadata-Version: 2.1
Name: simple-pyyuque
Version: 0.1.3
Summary: UNKNOWN
Home-page: https://github.com/Xarrow/simple-pyyuque
Author: helixcs
Author-email: zhangjian12424@gmail.com
License: MIT
Keywords: yuque lark pyyuque
Platform: UNKNOWN
Classifier: License :: OSI Approved :: MIT License
Classifier: Programming Language :: Python
Classifier: Programming Language :: Python :: 3.6
Classifier: Programming Language :: Python :: Implementation :: CPython
Classifier: Programming Language :: Python :: Implementation :: PyPy
Requires-Python: >=3.6
Requires-Dist: requests
